{"title":"펀샵 ─ 펀테나 ─ 패션/시계/가방","url":"https://www.funshop.co.kr/Story/FuntennaList#page=1&categoryNo=7&order=0&keyword=","favicon":"https://www.funshop.co.kr/Story/favicon.ico","elements":[{"title":"에이수스, ROG CETRA TRUE WIRELESS PRO 공개","contents":"좋은 무선이 레이턴시가 얼마라고? 유선은 '0' 이다!","link":"https://www.funshop.co.kr/Story/FuntennaView/19522#","retrieved":1658275200000,"image":"https://cdn.funshop.co.kr/abroad/039/19522/thumbnail_1.jpg"},{"title":"오데마 피게, 로열 오크 오프쇼어 뮤직 에디션 출시","contents":"오옷...젊은감성의 로열 오크","link":"https://www.funshop.co.kr/Story/FuntennaView/19521#","retrieved":1658275200000,"image":"https://cdn.funshop.co.kr/abroad/039/19521/thumbnail_1.jpg"},{"title":"Levante, 완전방수 모듈러 확장 백팩","contents":"완전 방수 백팩이면서 기능확장이 가능한 백팩","link":"https://www.funshop.co.kr/Story/FuntennaView/19520#","retrieved":1658275200000,"image":"https://cdn.funshop.co.kr/abroad/039/19520/thumbnail_1.jpg"},{"title":"노키아, 피처폰 5710 XpressAudio 출시","contents":"피처폰이지만 나름 신박한 디테일이..","link":"https://www.funshop.co.kr/Story/FuntennaView/19519#","retrieved":1658275200000,"image":"https://cdn.funshop.co.kr/abroad/039/19519/thumbnail_1.jpg"},{"title":"포커스라이트, Vocaster 시리즈 출시 예정","contents":"팟캐스트 진행자들을 위한 합리적인 시스템","link":"https://www.funshop.co.kr/Story/FuntennaView/19518#","retrieved":1658188800000,"image":"https://cdn.funshop.co.kr/abroad/039/19518/thumbnail_1.jpg"},{"title":"Kingston, DataTraveler Max A타입 출시","contents":"DataTraveler Max의 A타입","link":"https://www.funshop.co.kr/Story/FuntennaView/19517#","retrieved":1658188800000,"image":"https://cdn.funshop.co.kr/abroad/039/19517/thumbnail_1.jpg"},{"title":"Huntkey, 서지보호 100W GaN 충전기 출시","contents":"안전에 신경을 쓴 100W 충전기","link":"https://www.funshop.co.kr/Story/FuntennaView/19516#","retrieved":1658188800000,"image":"https://cdn.funshop.co.kr/abroad/039/19516/thumbnail_1.jpg"},{"title":"예티, 로디 48 휠 쿨러","contents":"바퀴가 달린 대용량 쿨러","link":"https://www.funshop.co.kr/Story/FuntennaView/19514#","retrieved":1658188800000,"image":"https://cdn.funshop.co.kr/abroad/039/19514/thumbnail_1.jpg"}]}