{"title":"펀샵 ─ 펀테나 ─ 생활/주방","url":"https://www.funshop.co.kr/Story/FuntennaList#page=1&categoryNo=3&order=0&keyword=","favicon":"https://www.funshop.co.kr/Story/favicon.ico","elements":[{"title":"James Brand, Palmer 유틸리티 나이프","contents":"실용적이면서 멋진 디자인","link":"https://www.funshop.co.kr/Story/FuntennaView/19758#","retrieved":1666915200000,"image":"https://cdn.funshop.co.kr/abroad/039/19758/thumbnail_1.jpg"},{"title":"메갈로돈, NINDOIO 매크로 패드 출시","contents":"게임보이 어드밴스 그 형태 그대로!","link":"https://www.funshop.co.kr/Story/FuntennaView/19757#","retrieved":1666915200000,"image":"https://cdn.funshop.co.kr/abroad/039/19757/thumbnail_1.jpg"},{"title":"MUJJO, 아이폰용 풀 가죽 마그네틱 지갑 출시","contents":"스프링이 내장??","link":"https://www.funshop.co.kr/Story/FuntennaView/19756#","retrieved":1666915200000,"image":"https://cdn.funshop.co.kr/abroad/039/19756/thumbnail_1.jpg"},{"title":"바워스앤윌킨스, PX8 007 에디션 헤드폰 출시","contents":"\"Bond. James Bond.\"","link":"https://www.funshop.co.kr/Story/FuntennaView/19755#","retrieved":1666828800000,"image":"https://cdn.funshop.co.kr/abroad/039/19755/thumbnail_1.jpg"},{"title":"나이키, 에어조던 5 고어텍스 출시예정","contents":"고어텍스! 조던5! 서태웅!","link":"https://www.funshop.co.kr/Story/FuntennaView/19754#","retrieved":1666828800000,"image":"https://cdn.funshop.co.kr/abroad/039/19754/thumbnail_1.jpg"},{"title":"크리에이티브, MUVO Go 아웃도어 스피커 공개","contents":"IPX7 등급으로 어디에서든 음악을 감상","link":"https://www.funshop.co.kr/Story/FuntennaView/19753#","retrieved":1666828800000,"image":"https://cdn.funshop.co.kr/www/renew/common/d280x280.jpg"},{"title":"롤랜드, 50주년 기념 콘셉트 모델 피아노 공개","contents":"전자음악의 중심인곳에서 만드는 원목 피아노","link":"https://www.funshop.co.kr/Story/FuntennaView/19752#","retrieved":1666828800000,"image":"https://cdn.funshop.co.kr/abroad/039/19752/thumbnail_1.jpg"},{"title":"레고, 테이블 축구 출시","contents":"재밌긴 할것 같은데....레고 가격 왜이러냐..","link":"https://www.funshop.co.kr/Story/FuntennaView/19751#","retrieved":1666742400000,"image":"https://cdn.funshop.co.kr/abroad/039/19751/thumbnail_1.jpg"}]}