{"title":"펀샵 ─ 펀테나 ─ 취미/기타","url":"https://www.funshop.co.kr/Story/FuntennaList#page=1&categoryNo=8&order=0&keyword=","favicon":"https://www.funshop.co.kr/Story/favicon.ico","elements":[{"title":"일반자전거를 전기자전거로, DiskDrive","contents":"약간 특이한 방식의 전기자전거 키트.","link":"https://www.funshop.co.kr/Story/FuntennaView/19447#","retrieved":1655856000000,"image":"https://cdn.funshop.co.kr/abroad/038/19447/thumbnail_1.jpg"},{"title":"가와사키의 밸런스 오토바이, 일렉트로드","contents":"어린이들을 위한 전동 밸런스바이크","link":"https://www.funshop.co.kr/Story/FuntennaView/19446#","retrieved":1655856000000,"image":"https://cdn.funshop.co.kr/abroad/038/19446/thumbnail_1.jpg"},{"title":"허먼밀러, 제프 by 스튜디오 7.5 출시","contents":"클래식한 의자의 디자인에 최신 기능이 탑재","link":"https://www.funshop.co.kr/Story/FuntennaView/19445#","retrieved":1655856000000,"image":"https://cdn.funshop.co.kr/abroad/038/19445/thumbnail_1.jpg"},{"title":"베사스탠드로 띄운다, 라인스탠드","contents":"충전과 사용을 동시에","link":"https://www.funshop.co.kr/Story/FuntennaView/19444#","retrieved":1655856000000,"image":"https://cdn.funshop.co.kr/abroad/038/19444/thumbnail_1.jpg"},{"title":"푸마, 포르쉐 911 카레라 RS 2.7 50주년 기념 신발 출시","contents":"베이스는 푸마의 스웨이드","link":"https://www.funshop.co.kr/Story/FuntennaView/19443#","retrieved":1655769600000,"image":"https://cdn.funshop.co.kr/abroad/038/19443/thumbnail_1.jpg"},{"title":"파이널 판타지 7 리메이크 Part 2 공개","contents":"Rebirth..","link":"https://www.funshop.co.kr/Story/FuntennaView/19442#","retrieved":1655769600000,"image":"https://cdn.funshop.co.kr/abroad/038/19442/thumbnail_1.jpg"},{"title":"Audeze X Manny Marroquin, MM-500 출시","contents":"오디지의 기술력과 Manny Marroquin의 만남","link":"https://www.funshop.co.kr/Story/FuntennaView/19441#","retrieved":1655769600000,"image":"https://cdn.funshop.co.kr/abroad/038/19441/thumbnail_1.jpg"},{"title":"삼성, 크리에이터 용 모니터 뷰피니티 S8 출시","contents":"이제 고해상도 모니터는 모두 뷰피니티..","link":"https://www.funshop.co.kr/Story/FuntennaView/19440#","retrieved":1655769600000,"image":"https://cdn.funshop.co.kr/abroad/038/19440/thumbnail_1.jpg"}]}