{"title":"펀샵 ─ 펀테나 ─ PC/모바일","url":"https://www.funshop.co.kr/Story/FuntennaList#page=1&categoryNo=2&order=0&keyword=","favicon":"https://www.funshop.co.kr/Story/favicon.ico","elements":[{"title":"터틀비치, 벨로시티원 레이스 휠 및 페달 출시","contents":"제대로 된 레이싱경험을 위한 컨트롤러","link":"https://www.funshop.co.kr/Story/FuntennaView/20892#","retrieved":1705881600000,"image":"https://cdn.funshop.co.kr/www/renew/common/d280x280.jpg"},{"title":"맥키, DLZ 크리에이터 XS 공개","contents":"팟캐스트, 스트리밍에 최적화된 컴팩트 적응형 디지털 믹서","link":"https://www.funshop.co.kr/Story/FuntennaView/20891#","retrieved":1705881600000,"image":"https://cdn.funshop.co.kr/abroad/041/20891/thumbnail_1.jpg"},{"title":"인디아나 존스 -그레이트 서클-, 게임 플레이 트레일러 공개","contents":"정식 한글화!","link":"https://www.funshop.co.kr/Story/FuntennaView/20890#","retrieved":1705881600000,"image":"https://cdn.funshop.co.kr/www/renew/common/d280x280.jpg"},{"title":"[해외펀딩] 손으로 그린 시계 Halcyon 1.5","contents":"세상에서 가장 위대한 메이드 인 차이나.","link":"https://www.funshop.co.kr/Story/FuntennaView/20889#","retrieved":1705622400000,"image":"https://cdn.funshop.co.kr/abroad/041/20889/thumbnail_1.jpg"},{"title":"오디오 웨어러블 장치, Feelbelt","contents":"백팩도 있었던 기억이.....","link":"https://www.funshop.co.kr/Story/FuntennaView/20888#","retrieved":1705622400000,"image":"https://cdn.funshop.co.kr/abroad/041/20888/thumbnail_1.jpg"},{"title":"에이수스, ZenScreen Fold OLED 디스플레이 공개","contents":"휴대 가능한 접이식 모니터","link":"https://www.funshop.co.kr/Story/FuntennaView/20887#","retrieved":1705622400000,"image":"https://cdn.funshop.co.kr/abroad/041/20887/thumbnail_1.jpg"},{"title":"레이저, Aether 모니터 라이트바 공개","contents":"RGB...RGB Everywhere~","link":"https://www.funshop.co.kr/Story/FuntennaView/20886#","retrieved":1705622400000,"image":"https://cdn.funshop.co.kr/abroad/041/20886/thumbnail_1.jpg"},{"title":"FIIO, 휴대용 카세트 플레이어 CP13 공개","contents":"워크맨의 귀환","link":"https://www.funshop.co.kr/Story/FuntennaView/20885#","retrieved":1705536000000,"image":"https://cdn.funshop.co.kr/abroad/041/20885/thumbnail_1.jpg"}]}