{"title":"펀샵 ─ 펀테나 ─ 자동차/모터사이클","url":"https://www.funshop.co.kr/Story/FuntennaList#page=1&categoryNo=1&order=0&keyword=","favicon":"https://www.funshop.co.kr/Story/favicon.ico","elements":[{"title":"켄싱턴, Pro Fit Ergo TB450 및 TB550 출시","contents":"인체공학적인 엄지 트랙볼","link":"https://www.funshop.co.kr/Story/FuntennaView/20532#","retrieved":1692748800000,"image":"https://cdn.funshop.co.kr/www/renew/common/d280x280.jpg"},{"title":"람보르기니, 최초의 전기차 란자도르 공개","contents":"프로산게 같은 느낌이...","link":"https://www.funshop.co.kr/Story/FuntennaView/20531#","retrieved":1692748800000,"image":"https://cdn.funshop.co.kr/abroad/041/20531/thumbnail_1.jpg"},{"title":"커세어, PC DIY 정밀 툴킷 출시","contents":"커세어 답지 않은 가격....","link":"https://www.funshop.co.kr/Story/FuntennaView/20530#","retrieved":1692748800000,"image":"https://cdn.funshop.co.kr/www/renew/common/d280x280.jpg"},{"title":"에이수스, Vivobook S 15 OLED 베이프 에디션 출시","contents":"여전히 귀여운 베이비 마일로","link":"https://www.funshop.co.kr/Story/FuntennaView/20533#","retrieved":1692662400000,"image":"https://cdn.funshop.co.kr/abroad/041/20533/thumbnail_1.jpg"},{"title":"Nacon, RIG 600 Pro 게이밍 헤드셋 공개","contents":"쫀쫀한 헤드밴드를 가진 게이밍 헤드셋","link":"https://www.funshop.co.kr/Story/FuntennaView/20529#","retrieved":1692662400000,"image":"https://cdn.funshop.co.kr/abroad/041/20529/thumbnail_1.jpg"},{"title":"삼성, 프리스타일 프로젝터 2세대 출시","contents":"가격은 내리고 성능은 올리고","link":"https://www.funshop.co.kr/Story/FuntennaView/20528#","retrieved":1692662400000,"image":"https://cdn.funshop.co.kr/abroad/041/20528/thumbnail_1.jpg"},{"title":"Epomaker, TH80-X 무선 기계식키보드 출시","contents":"깨물어 먹고싶은 달콤한 디자인","link":"https://www.funshop.co.kr/Story/FuntennaView/20527#","retrieved":1692576000000,"image":"https://cdn.funshop.co.kr/abroad/041/20527/thumbnail_1.jpg"},{"title":"Technics, 무선 이어버드 EAH-AZ40M2 출시","contents":"턴테이블 만으로 유명한 브랜드라는건 옛말","link":"https://www.funshop.co.kr/Story/FuntennaView/20526#","retrieved":1692576000000,"image":"https://cdn.funshop.co.kr/abroad/041/20526/thumbnail_1.jpg"}]}