{"title":"펀샵 ─ 펀테나 ─ 취미/기타","url":"https://www.funshop.co.kr/Story/FuntennaList#page=1&categoryNo=8&order=0&keyword=","favicon":"https://www.funshop.co.kr/Story/favicon.ico","elements":[{"title":"에디파이어, W820NB Plus 무선 헤드폰 공개","contents":"가성비의 노캔 무선 헤드폰","link":"https://www.funshop.co.kr/Story/FuntennaView/20294#","retrieved":1685491200000,"image":"https://cdn.funshop.co.kr/abroad/040/20294/thumbnail_1.jpg"},{"title":"'드래곤퀘스트 다이의 대모험 인피니티 스트랏슈' 출시일 공개","contents":"아방 스트랏슈!!!!!!!!!!!!!","link":"https://www.funshop.co.kr/Story/FuntennaView/20293#","retrieved":1685491200000,"image":"https://cdn.funshop.co.kr/abroad/040/20293/thumbnail_1.jpg"},{"title":"중국 맥도날드, 맥너겟 테트리스 출시","contents":"아 뭐야...한국도 내줘요...","link":"https://www.funshop.co.kr/Story/FuntennaView/20292#","retrieved":1685491200000,"image":"https://cdn.funshop.co.kr/abroad/040/20292/thumbnail_1.jpg"},{"title":"[해외펀딩] 16:10 화면비의 6.7인치 E-ink 전자책","contents":"이럴거면 차라리 폰으로 만들지.","link":"https://www.funshop.co.kr/Story/FuntennaView/20295#","retrieved":1685404800000,"image":"https://cdn.funshop.co.kr/abroad/040/20295/thumbnail_1.jpg"},{"title":"벨킨, BoostCharge Pro 파워 뱅크 출시","contents":"애플워치 울트라도 호환","link":"https://www.funshop.co.kr/Story/FuntennaView/20291#","retrieved":1685404800000,"image":"https://cdn.funshop.co.kr/abroad/040/20291/thumbnail_1.jpg"},{"title":"펜더, 휴대용 스피커 겸 엠프 Fender RIFF 출시","contents":"휴대용 기타엠프로 혹은 블루투스 스피커로..","link":"https://www.funshop.co.kr/Story/FuntennaView/20290#","retrieved":1685404800000,"image":"https://cdn.funshop.co.kr/abroad/040/20290/thumbnail_1.jpg"},{"title":"코나미, 메탈기어 솔리드 3 리메이크 출시예정","contents":"코지마가 없는 메탈기어..","link":"https://www.funshop.co.kr/Story/FuntennaView/20289#","retrieved":1685404800000,"image":"https://cdn.funshop.co.kr/abroad/040/20289/thumbnail_1.jpg"},{"title":"[해외펀딩] 혁신적인 모듈형 기계식 무선 키보드 Naya Create.","contents":"오늘 밤 주인공은 Naya Na Naya Create.","link":"https://www.funshop.co.kr/Story/FuntennaView/20288#","retrieved":1685059200000,"image":"https://cdn.funshop.co.kr/abroad/040/20288/thumbnail_1.jpg"}]}