{"title":"펀샵 ─ 펀테나 ─ 패션/시계/가방","url":"https://www.funshop.co.kr/Story/FuntennaList#page=1&categoryNo=7&order=0&keyword=","favicon":"https://www.funshop.co.kr/Story/favicon.ico","elements":[{"title":"이케아, 공기질 모니터 기기 출시예정","contents":"Vindstyrka....이거 어떻게 읽어야되지..","link":"https://www.funshop.co.kr/Story/FuntennaView/20056#","retrieved":1677110400000,"image":"https://cdn.funshop.co.kr/abroad/040/20056/thumbnail_1.jpg"},{"title":"지속가능한 무선 이어버드, Majority Tru Bio","contents":"생분해성 재질로 제작된 이어버드","link":"https://www.funshop.co.kr/Story/FuntennaView/20054#","retrieved":1677110400000,"image":"https://cdn.funshop.co.kr/abroad/040/20054/thumbnail_1.jpg"},{"title":"필립스의 수면용 헤드폰","contents":"불안한 수면패턴을 개선시켜주는 헤드폰.....앗...내가 사야되나..","link":"https://www.funshop.co.kr/Story/FuntennaView/20053#","retrieved":1677110400000,"image":"https://cdn.funshop.co.kr/abroad/040/20053/thumbnail_1.jpg"},{"title":"귀여운 패밀리 로봇, EBO X","contents":"집안의 다양한 상황을 감지하고 대응하는 보안로봇.","link":"https://www.funshop.co.kr/Story/FuntennaView/20038#","retrieved":1677110400000,"image":"https://cdn.funshop.co.kr/abroad/040/20038/thumbnail_1.jpg"},{"title":"티타늄으로 제작된 Ti 유틸리티 나이프","contents":"티타늄으로 만들어진 EDC 나이프","link":"https://www.funshop.co.kr/Story/FuntennaView/20061#","retrieved":1677456000000,"image":"https://cdn.funshop.co.kr/abroad/040/20061/thumbnail_1.jpg"},{"title":"ProtoArc, 모듈식 2 in 1 허브 마우스","contents":"USB 허브와 마우스의 만남...","link":"https://www.funshop.co.kr/Story/FuntennaView/20051#","retrieved":1677024000000,"image":"https://cdn.funshop.co.kr/abroad/040/20051/thumbnail_1.jpg"},{"title":"Q, 퀵릴리스 티타늄 키체인 카라비너","contents":"쉽게 분리와 결합이 가능한 퀵릴리스 타입","link":"https://www.funshop.co.kr/Story/FuntennaView/20050#","retrieved":1677024000000,"image":"https://cdn.funshop.co.kr/abroad/040/20050/thumbnail_1.jpg"},{"title":"Superdock, 데스크탑 충전스테이션","contents":"충전뿐만 아니라 다양한 데이터관련 기능까지 탑재","link":"https://www.funshop.co.kr/Story/FuntennaView/20049#","retrieved":1677024000000,"image":"https://cdn.funshop.co.kr/abroad/040/20049/thumbnail_1.jpg"}]}