{"title":"펀샵 ─ 펀테나 ─ 아웃도어/스포츠","url":"https://www.funshop.co.kr/Story/FuntennaList#page=1&categoryNo=4&order=0&keyword=","favicon":"https://www.funshop.co.kr/Story/favicon.ico","elements":[{"title":"베이어다이나믹, VERIO 200 출시","contents":"베이어다이나믹 최초 오픈형 무선 이어버드","link":"https://www.funshop.co.kr/Story/FuntennaView/21260#","retrieved":1719446400000,"image":"https://cdn.funshop.co.kr/abroad/042/21260/thumbnail_1.jpg"},{"title":"아디다스 X JJJJOUND X 주제 무리뉴 라인업 공개","contents":"JJJJOUND에 무리뉴까지?","link":"https://www.funshop.co.kr/Story/FuntennaView/21259#","retrieved":1719446400000,"image":"https://cdn.funshop.co.kr/abroad/042/21259/thumbnail_1.jpg"},{"title":"IQUNIX, EZ 시리즈 HE 게이밍 키보드 공개","contents":"프로 게이머들 못지 않은 장비로 내 실력을.....안되려나?","link":"https://www.funshop.co.kr/Story/FuntennaView/21258#","retrieved":1719446400000,"image":"https://cdn.funshop.co.kr/abroad/042/21258/thumbnail_1.jpg"},{"title":"Anker, Zolo 파워뱅크 출시","contents":"내장 케이블이 있는 대용량 파워뱅크","link":"https://www.funshop.co.kr/Story/FuntennaView/21257#","retrieved":1719360000000,"image":"https://cdn.funshop.co.kr/abroad/042/21257/thumbnail_1.jpg"},{"title":"카시오, 지샥 GBD-300 시리즈 공개","contents":"스마트워치라고 하기엔 턱없지만 지샥이라고 하면....납득?","link":"https://www.funshop.co.kr/Story/FuntennaView/21256#","retrieved":1719360000000,"image":"https://cdn.funshop.co.kr/abroad/042/21256/thumbnail_1.jpg"},{"title":"팀그룹, X1 MAX USB 메모리 공개","contents":"USB 3.2 Gen2 x1 타입으로 구현하는 빠른속도","link":"https://www.funshop.co.kr/Story/FuntennaView/21255#","retrieved":1719360000000,"image":"https://cdn.funshop.co.kr/abroad/042/21255/thumbnail_1.jpg"},{"title":"에이수스, 로그 아처 에르고에어 게이밍 백팩 공개","contents":"스타일과 기능성을 동시에","link":"https://www.funshop.co.kr/Story/FuntennaView/21253#","retrieved":1719273600000,"image":"https://cdn.funshop.co.kr/abroad/042/21253/thumbnail_1.jpg"},{"title":"레이저, 데스에더 V3 하이퍼스피드 출시","contents":"프로를 위한 경량 게이밍 마우스","link":"https://www.funshop.co.kr/Story/FuntennaView/21252#","retrieved":1719273600000,"image":"https://cdn.funshop.co.kr/www/renew/common/d280x280.jpg"}]}